{
  "list": "2",
  "isEnd": true,
  "article": [
    {
      "title": "#Geek Jam# 白日梦 | 他老爸把杨利伟送上太空，他把我们带进虚拟时空",
      "date": "2017年01月02日",
      "image": "http://mmbiz.qpic.cn/mmbiz_jpg/GbFHyvibyboakUXOFPg89m9mUIPIiaklUzqmAU1vAsGryxVFqTjx45l0Jroeo6icKzQMIq6VlWNE4vLYlbZb9Nwmw/640?wxfrom=100&wx_fmt=jpeg",
      "desc": "与大众合作，创造世界最大的虚拟现实发布会。他们会开启VR商用的未来吗？",
      "user_name": "诺亦腾",
      "user_id": "1",
      "user_avatar": "https://app.geek2startup.com/json/avatar_1.png",
      "mode": "aspectFill"
    },
    {
      "title": "#Geek Jam# 在北京的雾霾里，他拍下了全世界的蓝天",
      "date": "2017年01月02日",
      "image": "http://mmbiz.qpic.cn/mmbiz_jpg/GbFHyvibyboam5QrBWlLT8RG7OLHCjuH9dZgNyeEpdwAUojcIzwv3xMhx1atZLia9DqGJpvja4YNDlCtMN4sLibWw/640?wxfrom=100&wx_fmt=jpeg",
      "desc": "他们在 Kickstarter 众筹68万美金， 单月出货 3000台 ，创造了同品类的最高筹款纪录与出货纪录。",
      "user_name": "肖军涛",
      "user_id": "2",
      "user_avatar": "https://app.geek2startup.com/json/avatar_2.png",
      "mode": "aspectFill"
    },
    {
      "title": "#Geek Jam# 为了做这件事，他们一等就是三十年",
      "date": "2017年01月02日",
      "image": "http://mmbiz.qpic.cn/mmbiz_jpg/GbFHyvibyboZXicF1aEKbpfA1IXmDImNeIkV5okqn7XcOE7D09FTPdpEcURicdckMAYR595J7DrBobZUvRwt1Yafw/640?wxfrom=100&wx_fmt=jpeg",
      "desc": "张爱玲说，创业要趁早； 大叔们说，现在刚刚好！",
      "user_name": "唐波",
      "user_id": "3",
      "user_avatar": "https://app.geek2startup.com/json/avatar_3.png",
      "mode": "aspectFill"
    },
    {
      "title": "＃吐司推荐＃《你的名字》魅力太大,一位粉丝竟做出同款 App",
      "date": "2017年01月02日",
      "image": "http://mmbiz.qpic.cn/mmbiz_jpg/GbFHyvibyboY1jZtmib5UyqlCLN2t4gkjIpFxfUUiaicBANeQA94B2xSLBwCauW20AJ6tLwbwUtOj6REiaY2rvnuhwQ/640?wxfrom=100&wx_fmt=jpeg",
      "desc": "被电影《你的名字》刷屏了吗吐司君作为爱日漫的资深宅男必须是看首映啊结果一个大男淫活生生哭到劈叉12月2日在国",
      "user_name": "DA-夏",
      "user_id": "4",
      "user_avatar": "https://app.geek2startup.com/json/avatar_4.png",
      "mode": "aspectFill"
    }
  ]
}
